README.rst
setup.cfg
setup.py
flake8_fill_one_line/__init__.py
flake8_fill_one_line/check.py
flake8_fill_one_line/utils.py
flake8_fill_one_line.egg-info/PKG-INFO
flake8_fill_one_line.egg-info/SOURCES.txt
flake8_fill_one_line.egg-info/dependency_links.txt
flake8_fill_one_line.egg-info/entry_points.txt
flake8_fill_one_line.egg-info/requires.txt
flake8_fill_one_line.egg-info/top_level.txt
flake8_fill_one_line/analyzers/call_analyzer.py
flake8_fill_one_line/analyzers/def_analyzer.py
flake8_fill_one_line/analyzers/if_analyzer.py
flake8_fill_one_line/analyzers/if_exp_analyzer.py
flake8_fill_one_line/analyzers/import_analyzer.py
flake8_fill_one_line/analyzers/with_analyzer.py
tests/test_flake8_fill_one_line.py