Metadata-Version: 2.1
Name: flake8-fill-one-line
Version: 0.4.1
Summary: A Flake8 plugin to ensure an expression can be written in one line without exceeding the maximum length limit
Home-page: https://github.com/dronperminov/flake8-fill-one-line
License: MIT
Classifier: License :: OSI Approved :: MIT License
Classifier: Programming Language :: Python :: 3
Classifier: Programming Language :: Python :: 3 :: Only
Classifier: Programming Language :: Python :: Implementation :: CPython
Requires-Python: >=3.8
Requires-Dist: flake8>=3.7
Requires-Dist: astunparse>=1.6
